{
  "users": [
    {
      "firstName": "Nguyễn",
      "lastName": "Bảo Anh",
      "gender": "Nam",
      "email": "minhchico300kc@gmail.com",
      "password": "123456789",
      "dateOfBirth": "2003-02-07T17:00:00.000Z",
      "avatarImage": "",
      "id": 1
    },
    {
      "firstName": "Trần",
      "lastName": "Hưng",
      "gender": "Nam",
      "email": "tranhung@gmail.com",
      "password": "12345678",
      "dateOfBirth": "1999-12-02T17:00:00.000Z",
      "avatarImage": "",
      "id": 2
    },
    {
      "firstName": "Lê",
      "lastName": "Huy",
      "gender": "Khác",
      "email": "huylq@ptit.edu.vn",
      "password": "123456789",
      "dateOfBirth": "2002-12-04T17:00:00.000Z",
      "avatarImage": "",
      "id": 3
    },
    {
      "firstName": "Nguyễn",
      "lastName": "Bằng",
      "gender": "Nam",
      "email": "bangnguyen@gmail.com",
      "password": "12345678",
      "dateOfBirth": "2022-12-02T17:00:00.000Z",
      "avatarImage": "",
      "id": 4
    }
  ],
  "students": [
    {
      "fullName": "Nguyễn Quang Hạnhdzdz",
      "gender": "Nam",
      "dateOfBirth": "2005-01-07T12:48:54.143Z",
      "address": "Bến Tre",
      "email": "hanhnq@gmail.com",
      "schoolYear": "2020",
      "studentCode": "B20DCCN225",
      "majors": "Công nghệ thông tin",
      "uid": 1,
      "id": 2
    },
    {
      "fullName": "Riku Kawasaki",
      "gender": "Nam",
      "dateOfBirth": "1998-02-13T13:18:22.000Z",
      "address": "Hải Phòng",
      "email": "maroonrk@gmail.com",
      "schoolYear": "2021",
      "studentCode": "B21DCAT432",
      "majors": "An toàn thông tin",
      "uid": 1,
      "id": 12
    },
    {
      "fullName": "Tran Ngoc Anh Khoa",
      "gender": "Nam",
      "dateOfBirth": "2023-01-03T17:00:00.000Z",
      "address": "Cà Mau",
      "email": "khoatran@gmail.com",
      "schoolYear": "2021",
      "studentCode": "B21DCMR584",
      "majors": "Marketing",
      "uid": 1,
      "id": 14
    },
    {
      "fullName": "Harry Maguire",
      "gender": "Nam",
      "dateOfBirth": "1993-01-14T17:00:00.000Z",
      "address": "Đắk Lắk",
      "email": "hm@gmail.com",
      "schoolYear": "2019",
      "studentCode": "B19DCQT147",
      "majors": "Quản trị kinh doanh",
      "uid": 1,
      "id": 17
    },
    {
      "fullName": "Lê Thu Phương",
      "gender": "Nữ",
      "dateOfBirth": "2002-01-05T15:41:54.000Z",
      "address": "Hà Nội",
      "email": "phuongle@gmail.com",
      "schoolYear": "2019",
      "studentCode": "B19DCMR247",
      "majors": "Marketing",
      "uid": 1,
      "id": 18
    },
    {
      "fullName": "Trần Thị Thu",
      "gender": "Nữ",
      "dateOfBirth": "2001-01-15T15:43:07.327Z",
      "address": "Bắc Ninh",
      "email": "thutran@hotmail.com",
      "schoolYear": "2021",
      "studentCode": "B21DCTM997",
      "majors": "Thương mại điện tử",
      "uid": 1,
      "id": 19
    },
    {
      "fullName": "ptit2",
      "gender": "Khác",
      "dateOfBirth": "2001-01-15T15:43:49.076Z",
      "address": "Hưng Yên",
      "email": "ptit2@gmail.com",
      "schoolYear": "2019",
      "studentCode": "B19DCKT478",
      "majors": "Kế toán",
      "uid": 1,
      "id": 20
    },
    {
      "fullName": "ptit3Edit",
      "gender": "Nam",
      "dateOfBirth": "2002-01-19T15:44:22.000Z",
      "address": "Khánh Hòa",
      "email": "ptit3edit@gmail.com",
      "schoolYear": "2021",
      "studentCode": "B21DCAT201",
      "majors": "An toàn thông tin",
      "uid": 1,
      "id": 21
    },
    {
      "fullName": "ptit5",
      "gender": "Nữ",
      "dateOfBirth": "2023-01-02T17:00:00.000Z",
      "address": "Quảng Ninh",
      "email": "ptit5@gmail.com",
      "schoolYear": "2020",
      "studentCode": "B20DCKT875",
      "majors": "Kế toán",
      "uid": 1,
      "id": 22
    },
    {
      "fullName": "òprfp",
      "gender": "Nữ",
      "dateOfBirth": "2005-01-13T06:30:00.000Z",
      "address": "Cao Bằng",
      "email": "eodpwr@gmail.com",
      "schoolYear": "2019",
      "studentCode": "B19DCQT409",
      "majors": "Quản trị kinh doanh",
      "uid": 1,
      "id": 23
    }
  ]
}
